zmanim_core_bindings-0.2.7.dist-info/METADATA
zmanim_core_bindings-0.2.7.dist-info/WHEEL
zmanim_core_bindings-0.2.7.dist-info/licenses/LICENSE
zmanim_py/__init__.py
zmanim_py/libzmanim_core.dylib
zmanim_py/zmanim_core.py
zmanim_core_bindings-0.2.7.dist-info/RECORD
