Metadata-Version: 2.4
Name: zmanim-core-bindings
Version: 0.2.7
Classifier: Programming Language :: Rust
Classifier: Programming Language :: Python :: Implementation :: CPython
Classifier: Programming Language :: Python :: Implementation :: PyPy
License-File: LICENSE
License-File: LICENSE
Summary: Bindings to the zmanim-core rust library
Keywords: zmanim,jewish,calendar,astronomy,time,zmanim-core
Author-email: Moshe Dicker <dickermoshe@gmail.com>
Requires-Python: >=3.8
Project-URL: Homepage, https://github.com/dickermoshe/zmanim-core/blob/main/PYTHON.README.md
